README.rst
setup.py
gepapy/__init__.py
gepapy/flow_shop.py
gepapy/flow_shop.pyi
gepapy/job_shop.py
gepapy/job_shop.pyi
gepapy/operations.py
gepapy/operations.pyi
gepapy/py.typed
gepapy/single_machine.py
gepapy/single_machine.pyi
gepapy.egg-info/PKG-INFO
gepapy.egg-info/SOURCES.txt
gepapy.egg-info/dependency_links.txt
gepapy.egg-info/requires.txt
gepapy.egg-info/top_level.txt
gepapy/exceptions/__init__.py
gepapy/exceptions/operations.py
gepapy/kernels/__init__.py
gepapy/kernels/crossA0001.py
gepapy/kernels/crossA0001.pyi
gepapy/kernels/fitnessA0001.py
gepapy/kernels/fitnessA0001.pyi
gepapy/kernels/mutationA0001.py
gepapy/kernels/mutationA0001.pyi
gepapy/kernels/permutationA0001.py
gepapy/kernels/permutationA0001.pyi
gepapy/kernels/py.typed
gepapy/kernels/sortA0001.py